stplanpy/__init__.py
stplanpy/acs.py
stplanpy/cycle.py
stplanpy/dist.py
stplanpy/geo.py
stplanpy/od.py
stplanpy/route.py
stplanpy/srtm.py
stplanpy/stats.py
stplanpy-0.3.0.dist-info/LICENSE
stplanpy-0.3.0.dist-info/METADATA
stplanpy-0.3.0.dist-info/WHEEL
stplanpy-0.3.0.dist-info/top_level.txt
stplanpy-0.3.0.dist-info/RECORD
