Metadata-Version: 2.1
Name: stplanpy
Version: 0.3.0
Summary: The Sustainable Transportation Planner for Python is a library focused on active transportation and transit. It was inspired by the stplanr library for R
Home-page: https://github.com/pctBayArea/stplanpy
Author: Arnout Boelens
Author-email: ampboelens@gmail.com
License: UNKNOWN
Platform: UNKNOWN
Classifier: Development Status :: 2 - Pre-Alpha
Classifier: Intended Audience :: Science/Research
Classifier: Intended Audience :: Developers
Classifier: License :: OSI Approved :: GNU General Public License v3 or later (GPLv3+)
Classifier: Operating System :: POSIX :: Linux
Classifier: Operating System :: MacOS
Classifier: Operating System :: Microsoft :: Windows
Classifier: Programming Language :: Python :: 3
Requires-Dist: numpy
Requires-Dist: shapely (<=2.0)
Requires-Dist: pandas
Requires-Dist: pandas-flavor
Requires-Dist: geopandas (>=0.9)
